llmsearch/__init__.py
llmsearch/patches/__init__.py
llmsearch/patches/transformers_monkey_patch.py
llmsearch/scripts/__init__.py
llmsearch/scripts/stopping_criteria.py
llmsearch/tuner/__init__.py
llmsearch/tuner/tuner.py
llmsearch/utils/__init__.py
llmsearch/utils/common_utils.py
llmsearch/utils/gen_utils.py
llmsearch/utils/logging_utils.py
llmsearch/utils/mem_utils.py
llmsearch/utils/model_downloader.py
llmsearch/utils/model_utils.py
llmsearch-0.1.0.dist-info/LICENSE
llmsearch-0.1.0.dist-info/METADATA
llmsearch-0.1.0.dist-info/WHEEL
llmsearch-0.1.0.dist-info/RECORD
