Metadata-Version: 2.1
Name: llmsearch
Version: 0.1.0
Summary: Find the Best Generation Parameters for your LLM & Dataset
Author: Praful932
Author-email: praful.mohanan@gmail.com
Requires-Python: >=3.8.1,<4.0
Classifier: Programming Language :: Python :: 3
Classifier: Programming Language :: Python :: 3.9
Classifier: Programming Language :: Python :: 3.10
Classifier: Programming Language :: Python :: 3.11
Classifier: Programming Language :: Python :: 3.12
Provides-Extra: pynvml
Requires-Dist: datasets (>=2.11.0,<3.0.0)
Requires-Dist: numpy (>=1.17)
Requires-Dist: nvidia-ml-py3 (>=7.352.0,<8.0.0) ; extra == "pynvml"
Requires-Dist: psutil (>=5.9)
Requires-Dist: scikit-learn (>=1.3,<2.0)
Requires-Dist: torch (>=1.1) ; sys_platform != "darwin"
Requires-Dist: torch (>=2.1) ; sys_platform == "darwin"
Requires-Dist: tqdm (>=4.27,<5.0)
Requires-Dist: transformers[sentencepiece] (>=4.27.4,<5.0.0)
